commoner/__init__.py
commoner/brush/__init__.py
commoner/math/__init__.py
commoner/types/__init__.py
commoner-0.5.0.dist-info/METADATA
commoner-0.5.0.dist-info/WHEEL
commoner-0.5.0.dist-info/RECORD
