Metadata-Version: 2.1
Name: commoner
Version: 0.5.0
Summary: Commoner provides a set of common functions and classes for Python projects.
License: MIT
Author: uncenter
Author-email: me@uncenter.org
Requires-Python: >=3.11,<4.0
Classifier: License :: OSI Approved :: MIT License
Classifier: Programming Language :: Python :: 3
Classifier: Programming Language :: Python :: 3.11
Requires-Dist: numpy (>=1.24.2,<2.0.0)
